README.md
setup.cfg
setup.py
phyphy.egg-info/PKG-INFO
phyphy.egg-info/SOURCES.txt
phyphy.egg-info/dependency_links.txt
phyphy.egg-info/requires.txt
phyphy.egg-info/top_level.txt
src/__init__.py
src/analysis.py
src/extractor.py
src/hyphy.py